bfcl/__init__.py
bfcl/bfcl.py
bfcl-1.0.1.dist-info/LICENSE
bfcl-1.0.1.dist-info/METADATA
bfcl-1.0.1.dist-info/WHEEL
bfcl-1.0.1.dist-info/top_level.txt
bfcl-1.0.1.dist-info/RECORD
