Metadata-Version: 2.1
Name: bfcl
Version: 1.0.1
Summary: Python library for working with circuit definitions represented using the Bristol Fashion.
Home-page: https://github.com/nthparty/bfcl
Author: Andrei Lapets
Author-email: a@lapets.io
License: MIT
Platform: UNKNOWN
License-File: LICENSE
Requires-Dist: parts (~=1.3)
Requires-Dist: circuit (~=1.0)
